basecamp_chatbot/__init__.py
basecamp_chatbot/chatbot.py
basecamp_chatbot/exceptions.py
basecamp_chatbot/models.py
basecamp_chatbot/post_file.py
basecamp_chatbot/post_string.py
basecamp_chatbot/rest_adapter.py
basecamp_chatbot-2024.8.22.4.dist-info/METADATA
basecamp_chatbot-2024.8.22.4.dist-info/WHEEL
basecamp_chatbot-2024.8.22.4.dist-info/entry_points.txt
basecamp_chatbot-2024.8.22.4.dist-info/licenses/LICENSE
basecamp_chatbot-2024.8.22.4.dist-info/RECORD
