Metadata-Version: 2.3
Name: basecamp_chatbot
Version: 2024.8.22.4
Summary: A Python library for the Basecamp 3 chatbot API
Project-URL: Homepage, https://github.com/uwmadison-chm/basecamp-chatbot
Project-URL: Issues, https://github.com/uwmadison-chm/basecamp-chatbot/issues
Author-email: Nicholas Vanhaute <nvanhaute@wisc.edu>
License-File: LICENSE
Classifier: License :: OSI Approved :: MIT License
Classifier: Operating System :: OS Independent
Classifier: Programming Language :: Python :: 3
Requires-Python: >=3.8
Requires-Dist: certifi>=2024.7.4
Requires-Dist: charset-normalizer>=3.3.2
Requires-Dist: docopt-ng>=0.9.0
Requires-Dist: idna>=3.7
Requires-Dist: requests==2.32.3
Requires-Dist: urllib3==2.2.2
